odi/__init__.py
odi/__version__.py
odi/exception.py
odi/cli/__init__.py
odi/cli/cli.py
odi/cli/context.py
odi/cli/command/__init__.py
odi/cli/command/pull.py
odi/client/__init__.py
odi/client/entry.py
odi/client/request.py
odi/client/storage.py
odi/dataset/__init__.py
odi/util/__init__.py
odi/util/ui.py
odimock-0.0.2a0.dist-info/LICENSE
odimock-0.0.2a0.dist-info/METADATA
odimock-0.0.2a0.dist-info/WHEEL
odimock-0.0.2a0.dist-info/entry_points.txt
odimock-0.0.2a0.dist-info/top_level.txt
odimock-0.0.2a0.dist-info/RECORD
